{
  "resourceType": "ClinicalUseDefinition",
  "id": "db05332-idiopathic-aplastic-anemia",
  "type": "indication",
  "subject": [
    {
      "reference": "MedicationKnowledge/db05332"
    }
  ],
  "indication": {
    "diseaseSymptomProcedure": {
      "concept": {
        "coding": [
          {
            "system": "https://mytxgnn.yao.care/diseases",
            "code": "idiopathic-aplastic-anemia",
            "display": "idiopathic aplastic anemia"
          }
        ],
        "text": "idiopathic aplastic anemia"
      }
    }
  },
  "extension": [
    {
      "url": "https://mytxgnn.yao.care/fhir/StructureDefinition/evidence-level",
      "valueCode": "L5"
    },
    {
      "url": "https://mytxgnn.yao.care/fhir/StructureDefinition/source",
      "valueString": "TxGNN Knowledge Graph"
    }
  ]
}